reasoning_core/__init__.py
reasoning_core/downstream_eval.py
reasoning_core/generation_worker.py
reasoning_core/run_generate.sh
reasoning_core/template.py
reasoning_core/environments/reasoning_core_env/README.md
reasoning_core/environments/reasoning_core_env/pyproject.toml
reasoning_core/environments/reasoning_core_env/reasoning_core_env.py
reasoning_core/environments/reasoning_core_env/outputs/evals/reasoning-core-env--gpt-4.1-mini/19ee3b06/metadata.json
reasoning_core/environments/reasoning_core_env/outputs/evals/reasoning-core-env--gpt-4.1-mini/19ee3b06/results.jsonl
reasoning_core/resources/axioms_filtered.json.gz
reasoning_core/tasks/_logic_utils.py
reasoning_core/tasks/_reasoning_gym.py
reasoning_core/tasks/_sat_graph.py
reasoning_core/tasks/arithmetics.py
reasoning_core/tasks/causal_reasoning.py
reasoning_core/tasks/equation_system.py
reasoning_core/tasks/formal_maths.py
reasoning_core/tasks/grammar.py
reasoning_core/tasks/logic.py
reasoning_core/tasks/planning.py
reasoning_core/tasks/regex_following.py
reasoning_core/tasks/sequential_induction.py
reasoning_core/tasks/set_operations.py
reasoning_core/utils/__init__.py
reasoning_core/utils/udocker_process.py
reasoning_core-0.1.17.dist-info/METADATA
reasoning_core-0.1.17.dist-info/WHEEL
reasoning_core-0.1.17.dist-info/licenses/LICENSE
reasoning_core-0.1.17.dist-info/RECORD
