Metadata-Version: 2.4
Name: reasoning_core
Version: 0.1.17
Summary: A RL env with procedurally generated symbolic reasoning data
License-File: LICENSE
Requires-Dist: appdirs
Requires-Dist: beautifulsoup4
Requires-Dist: easydict
Requires-Dist: exrex
Requires-Dist: faker
Requires-Dist: funcy
Requires-Dist: inflection
Requires-Dist: lazy-object-proxy
Requires-Dist: multiprocess
Requires-Dist: networkx
Requires-Dist: nltk
Requires-Dist: num2words
Requires-Dist: numpy
Requires-Dist: pandas
Requires-Dist: pooch
Requires-Dist: prime
Requires-Dist: pyagrum
Requires-Dist: pyparsing
Requires-Dist: reasoning-gym
Requires-Dist: regex
Requires-Dist: requests
Requires-Dist: sympy
Requires-Dist: tarski
Requires-Dist: timeout-decorator
Requires-Dist: timeoutcontext
Requires-Dist: tqdm
Requires-Dist: udocker
Requires-Dist: unified-planning[pyperplan]
Requires-Dist: unigram
Requires-Dist: verifiers
Requires-Dist: xpflow
